iter/__init__.py
iter-0.0.0.dist-info/METADATA
iter-0.0.0.dist-info/WHEEL
iter-0.0.0.dist-info/top_level.txt
iter-0.0.0.dist-info/RECORD
