Metadata-Version: 2.1
Name: iter
Version: 0.0.0
Summary: Iter
Home-page: UNKNOWN
Author: UNKNOWN
Author-email: UNKNOWN
License: UNKNOWN
Platform: UNKNOWN
Classifier: Programming Language :: Python :: 3.7
Requires-Dist: pybiz
Requires-Dist: appyratus
Requires-Dist: pytest
Requires-Dist: ipdb
